rpa_tiktok/__init__.py
rpa_tiktok/api/BillApi.py
rpa_tiktok/api/LogisticsApi.py
rpa_tiktok/api/OptimizerApi.py
rpa_tiktok/api/OrderApi.py
rpa_tiktok/api/ProductApi.py
rpa_tiktok/api/ShopApi.py
rpa_tiktok/api/UnionApi.py
rpa_tiktok/api/__init__.py
rpa_tiktok/command/__init__.py
rpa_tiktok/command/bill/__init__.py
rpa_tiktok/command/bill/service/BillService.py
rpa_tiktok/command/bill/service/__init__.py
rpa_tiktok/command/logistics/__init__.py
rpa_tiktok/command/logistics/service/LogisticsService.py
rpa_tiktok/command/logistics/service/__init__.py
rpa_tiktok/command/order/__init__.py
rpa_tiktok/command/order/service/OrderService.py
rpa_tiktok/command/order/service/__init__.py
rpa_tiktok/command/product/__init__.py
rpa_tiktok/command/product/service/OptimizerService.py
rpa_tiktok/command/product/service/ProductService.py
rpa_tiktok/command/product/service/__init__.py
rpa_tiktok/command/shop/__init__.py
rpa_tiktok/command/shop/service/ShopService.py
rpa_tiktok/command/shop/service/__init__.py
rpa_tiktok/command/union/__init__.py
rpa_tiktok/command/union/service/UnionService.py
rpa_tiktok/command/union/service/__init__.py
rpa_tiktok/request/OrderRequest.py
rpa_tiktok/request/__init__.py
rpa_tiktok/service/TiktokService.py
rpa_tiktok/service/__init__.py
rpa_tiktok-1.0.12.dist-info/LICENSE
rpa_tiktok-1.0.12.dist-info/METADATA
rpa_tiktok-1.0.12.dist-info/WHEEL
rpa_tiktok-1.0.12.dist-info/top_level.txt
rpa_tiktok-1.0.12.dist-info/RECORD
