Metadata-Version: 2.1
Name: rpa_tiktok
Version: 1.0.12
Summary: RPA automated execution program for TikTok
Home-page: https://pypi.org/project/rpa-tiktok/
Author: Zhongshuizhou
Author-email: zhongshuizhou@qq.com
Classifier: Programming Language :: Python :: 3.8
Classifier: License :: OSI Approved :: MIT License
Classifier: Operating System :: OS Independent
Requires-Python: >=3.8
License-File: LICENSE
Requires-Dist: selenium==4.27.1
